MANIFEST.in
README.md
UNLICENSE
setup.py
tests.py
micromodels/__init__.py
micromodels/fields.py
micromodels/models.py
micromodels_ng.egg-info/PKG-INFO
micromodels_ng.egg-info/SOURCES.txt
micromodels_ng.egg-info/dependency_links.txt
micromodels_ng.egg-info/requires.txt
micromodels_ng.egg-info/top_level.txt